odoo/addons/base_sparse_field_list_support/README.rst
odoo/addons/base_sparse_field_list_support/__init__.py
odoo/addons/base_sparse_field_list_support/__manifest__.py
odoo/addons/base_sparse_field_list_support/i18n/base_sparse_field_list_support.pot
odoo/addons/base_sparse_field_list_support/i18n/it.po
odoo/addons/base_sparse_field_list_support/models/__init__.py
odoo/addons/base_sparse_field_list_support/models/fields.py
odoo/addons/base_sparse_field_list_support/readme/CONTRIBUTORS.md
odoo/addons/base_sparse_field_list_support/readme/DESCRIPTION.md
odoo/addons/base_sparse_field_list_support/static/description/icon.png
odoo/addons/base_sparse_field_list_support/static/description/index.html
odoo_addon_base_sparse_field_list_support-18.0.1.0.0.2.dist-info/METADATA
odoo_addon_base_sparse_field_list_support-18.0.1.0.0.2.dist-info/WHEEL
odoo_addon_base_sparse_field_list_support-18.0.1.0.0.2.dist-info/top_level.txt
odoo_addon_base_sparse_field_list_support-18.0.1.0.0.2.dist-info/RECORD
